runexp/__init__.py
runexp/argparse.py
runexp/config_file.py
runexp/dry_run.py
runexp/environment.py
runexp/parser_utils.py
runexp/py.typed
runexp/run_proc.py
runexp/slurm_env.py
runexp/slurm_utils.py
runexp/utils.py
runexp/wandb_utils.py
runexp-0.1.4.dist-info/METADATA
runexp-0.1.4.dist-info/WHEEL
runexp-0.1.4.dist-info/licenses/LICENSE
runexp-0.1.4.dist-info/RECORD
