Metadata-Version: 2.4
Name: runexp
Version: 0.1.4
Summary: Library to run experiment from argparse or config file with slurm
Project-URL: Homepage, https://github.com/maxime915/runexp
Project-URL: Bug Tracker, https://github.com/maxime915/runexp/issues
Author-email: Maxime Amodei <maxime.amodei@gmail.com>
License-File: LICENSE
Classifier: License :: OSI Approved :: MIT License
Classifier: Operating System :: POSIX :: Linux
Classifier: Programming Language :: Python :: 3
Requires-Python: >=3.10
Requires-Dist: psutil~=7.1.1
Requires-Dist: pydantic~=2.4
Requires-Dist: pyyaml~=6.0
